<DOMSymbolItem xmlns:xsi="http://www.w3.org/2001/XMLSchema-instance" xmlns="http://ns.adobe.com/xfl/2008/" name="player" itemID="50f71fd8-000006ad" linkageExportForAS="true" linkageClassName="PlayerArt" lastModified="1366754875" lastUniqueIdentifier="2">
  <timeline>
    <DOMTimeline name="player">
      <layers>
        <DOMLayer name="Layer 5" color="#4FFFFF">
          <frames>
            <DOMFrame index="0" keyMode="9728">
              <elements/>
            </DOMFrame>
          </frames>
        </DOMLayer>
        <DOMLayer name="Layer 6" color="#808080" current="true" isSelected="true">
          <frames>
            <DOMFrame index="0" keyMode="9728">
              <elements>
                <DOMShape isDrawingObject="true">
                  <matrix>
                    <Matrix a="-0.0037078857421875" b="0.999984741210938" c="-0.999984741210938" d="-0.0037078857421875" tx="16.9" ty="37.4"/>
                  </matrix>
                  <fills>
                    <FillStyle index="1">
                      <SolidColor alpha="0.996078431372549"/>
                    </FillStyle>
                  </fills>
                  <strokes>
                    <StrokeStyle index="1">
                      <SolidStroke scaleMode="normal" weight="0.1">
                        <fill>
                          <SolidColor color="#FF0000"/>
                        </fill>
                      </SolidStroke>
                    </StrokeStyle>
                  </strokes>
                  <edges>
                    <Edge fillStyle1="1" strokeStyle="1" edges="!-451 576[#FFFE4B.09 #2A9.B5 -440 845!-440 845[#FFFE44.E3 #3F0.56 -466 1148!-466 1148[#FFFE17.4E #507.7A -714 1080!-714 1080[#FFFC54.9B #368.AB -822 955.5!-822 955.5[#FFFD3F.51 #40E.27 -698 875!-698 875[#FFFD4C.AC #2C7.F4 -667 591!-667
 591[#FFFD7D.1C #1D6.04 -554 470!-554 470[#FFFE2E.FC #1D6.19 -451 576"/>
                  </edges>
                </DOMShape>
                <DOMShape isDrawingObject="true">
                  <matrix>
                    <Matrix a="-0.0037078857421875" b="0.999984741210938" c="0.999984741210938" d="0.0037078857421875" tx="-16.8" ty="38.25"/>
                  </matrix>
                  <fills>
                    <FillStyle index="1">
                      <SolidColor alpha="0.996078431372549"/>
                    </FillStyle>
                  </fills>
                  <strokes>
                    <StrokeStyle index="1">
                      <SolidStroke scaleMode="normal" weight="0.1">
                        <fill>
                          <SolidColor color="#FF0000"/>
                        </fill>
                      </SolidStroke>
                    </StrokeStyle>
                  </strokes>
                  <edges>
                    <Edge fillStyle1="1" strokeStyle="1" edges="
!-451 576[#FFFE4B.09 #2A9.B5 -440 845!-440 845[#FFFE44.E3 #3F0.56 -466 1148!-466 1148[#FFFE17.4E #507.7A -714 1080!-714 1080[#FFFC54.9B #368.AB -822 955.5!-822 955.5[#FFFD3F.51 #40E.27 -698 875!-698 875[#FFFD4C.AC #2C7.F4 -667 591!-667
 591[#FFFD7D.1C #1D6.04 -554 470!-554 470[#FFFE2E.FC #1D6.19 -451 576"/>
                  </edges>
                </DOMShape>
              </elements>
            </DOMFrame>
          </frames>
        </DOMLayer>
        <DOMLayer name="Layer 4" color="#FF4FFF">
          <frames>
            <DOMFrame index="0" keyMode="9728">
              <elements>
                <DOMShape>
                  <fills>
                    <FillStyle index="1">
                      <SolidColor color="#FFFFFF" alpha="0.996078431372549"/>
                    </FillStyle>
                  </fills>
                  <edges>
                    <Edge fillStyle0="1" edges="
!48 106[49 107 50 107!50 107|49 106!49 106|48 106!57 66[55 68 53 69!53 69|52 71!52 71|51 71!51 71|53 75!53 75[54 86 53 96!53 96|53 98!53 98|54 97!54 97[55 95 56 93!56 93|56 92!56 92[56 91 57 91!57 91|57 89!57 89[57 87 59 86!59 86|59 85
!59 85[58 82 58 80!58 80[58 78 58 76!58 76|58 74!58 74[56 71 57 69!57 69|58 66!58 66|57 66!61 68[61 69 60 72!60 72[62 75 60 79!60 79|61 78!61 78[61 #4E.E 61 80!61 80[#3D.1 #4D.C2 62 74!62 74[62 76 62 78!62 78[62 #5D.A 62 109.5!62 109.5
[#3E.18 #69.A 63 102!63 102[64 84 62 69!62 69|61 68!58 99|58 97!58 97[57 98 57 99!57 99|58 99"/>
                    <Edge fillStyle1="1" edges="
!89 99[90 96 91 93!91 93|92 94!92 94|93 94!93 94|94 95!94 95[94 99 93 103!93 103|93 104!93 104|94 104!94 104[95 104 96 104!96 104|98 106!98 106[96 109 95 111!95 111|93 112!93 112|93 115!93 115[92 117 91 120!91 120[#5A.04 120 90 119!90
 119[#59.FC #78.04 89 121!89 121|90 122!90 122|91 122!91 122[88 125 86 127!86 127[85 128 85 127!85 127[84 128 84 129!84 129|83 129!83 129|83 128!83 128|82 130!82 130|82 129!82 129|81 129!81 129|81 128!81 128[83 126 83 123!83 123|83 120
!83 120|82 120!82 120|81 118!81 118[82 118 82 117!82 117|82 115!82 115[82 114 83 113!83 113|83 108!83 108|84 108!84 108|84 107!84 107[85 106 86 105!86 105|86 104!86 104[86 103 87 103!87 103[88 100 89 98!89 98|89 99"/>
                    <Edge fillStyle0="1" edges="
!60 156|60 155!60 155[59 157 59 158!59 158|60 156!59 166|58 166!58 166|58 167!58 167|59 166!76 184|75 185!75 185|77 184!77 184|76 184"/>
                    <Edge fillStyle1="1" edges="
!92 176|92 175!92 175|93 176!93 176|92 176!97 182|97 183!97 183|96 181!96 181|97 182!95 178|94 178!94 178|95 177!95 177|95 178!97 190|98 190!98 190|98 191!98 191[97 191 97 190!98 193[99 192 99 194!99 194|99 197!99 197[#62.FA #C3.F5 98
 194!98 194|98 193"/>
                    <Edge fillStyle0="1" edges="
!72 190[73 189 73 188!73 188|72 189!72 189|72 190!54 194|53 195!53 195|54 195!54 195|54 194"/>
                    <Edge fillStyle1="1" edges="
!57 219[#39.1E #D9.E2 58 217!58 217|58 218!58 218[#39.2 218 57 219!55 219|57 220!57 220|56 220!56 220|55 219!55 224[54 225 53 226!53 226|53 225!53 225[54 224 56 223!56 223|55 224!156 150|156 152!156 152|155 151!155 151|155 150!155 150
|156 150!151 190|151 191!151 191|150 192!150 192|150 191!150 191[150 190 151 190!186 275|186 276!186 276|185 277!185 277|186 275!183 264|184 265!184 265|183 265!183 265|182 264!182 264|183 264!169 558|170 555!170 555|171 555!171 555[170
 556 169 558"/>
                    <Edge fillStyle0="1" edges="
!-67 119[-68 122 -67 126!-67 126[-67 127 -66 128!-66 128|-64 129!-64 129[-67 126 -67 123!-67 123[-66 121 -66 119!-66 119|-67 119!-62 119[-63 122 -63 125!-63 125|-63 126!-63 126[-63 128 -62 130!-62 130[-62 132 -62 135!-62 135|-62 136!-62
 136[-62 137 -62 139!-62 139|-63 141!-63 141[-62 141 -62 142!-62 142|-62 143!-62 143[-61 145 -59 148!-59 148|-59 147!-59 147|-58 147!-58 147[-57 137 -58 126!-58 126[-59 125 -58 125!-58 125|-58 121!-58 121|-59 120!-59 120[-60 117 -62 115
!-62 115|-63 115!-63 115|-62 117!-62 117[-62 118 -62 119!-152 173[-152 172 -153 172!-153 172|-153 173!-153 173|-152 174!-152 174|-152 173!-158 195[-158 201 -158 206!-158 206|-152 205!-152 205[-154 201 -156 196!-156 196|-157 195!-157 195
[-158 193 -158 195!-167 201|-166 201!-166 201|-166 200!-166 200|-167 199!-167 199|-167 201!-151 186|-149 188!-149 188|-149 187!-149 187[-150 186 -151 186!-148 193|-148 192!-148 192[#FFFF6B.06 192 -149 191!-149 191|-149 192!-149 192|-148
 193!-148 205|-148 206!-148 206|-147 207!-147 207[-147 206 -148 205"/>
                    <Edge fillStyle1="1" edges="
!-62 150[-62.125 149 -63 149!-63 149|-63 147!-63 147[-62.109375 #94.C8 -62 150!-93 183|-93 182!-93 182|-92 183!-92 183|-93 183!-93 185|-93 186!-93 186|-94 185!-94 185[-94 184 -93 185"/>
                    <Edge fillStyle0="1" edges="
!-78 177|-78 178!-78 178|-77 178!-77 178|-77 177!-77 177|-78 177!-56 159|-56 160!-56 160|-55 159!-55 159|-56 159!-54 160|-55 160!-55 160|-55 161!-55 161|-54 161!-54 161|-54 160"/>
                    <Edge fillStyle1="1" edges="
!-58 157[-59 156 -60 153!-60 153[-59 155 -58 156!-58 156|-58 157"/>
                    <Edge fillStyle0="1" edges="
!-53 167|-54 166!-54 166|-54 167!-54 167|-53 167!-52 174|-50 175!-50 175|-51 174!-51 174|-52 174!-51 181|-50 181!-50 181|-51 180!-51 180|-51 181!-67 169[-67 161 -67 153!-67 153[-68 163 -67 172!-67 172[-67 171 -67 169"/>
                    <Edge fillStyle1="1" edges="
!-95 198[-95.984375 #C6.FC -97 200!-97 200[-96.015625 #C6.F8 -97 197!-97 197|-97 196!-97 196|-96 194!-96 194[-96 196 -95 198"/>
                    <Edge fillStyle0="1" edges="
!-188 265|-189 265!-189 265|-187 266!-187 266|-188 265!-187 275[-187 276 -186 276!-186 276|-186 275!-186 275|-187 275"/>
                    <Edge fillStyle1="1" edges="
!-178 267[#FFFF4B.06 #108.06 -181 262!-181 262[#FFFF4A.FC 263 -182 263!-182 263[-182 260 -181 261!-181 261[-179 264 -178 267!-42 383|-43 383!-43 383|-43 382!-43 382|-42 383"/>
                    <Edge fillStyle0="1" edges="
!-173 537[-171 540 -169 541!-169 541[-171 539 -172 537!-172 537|-173 537"/>
                    <Edge cubics="!-77 177(;-77,177 -78,177 -78,177q-77 177 -78 177);"/>
                    <Edge cubics="!-78 177(;-78,177 -78,178 -78,178q-78 177 -78 178);"/>
                    <Edge cubics="!171 555(;170,556 170,556 169,558q171 555Q170 556q169 558);"/>
                    <Edge cubics="!169 558(;169,558 170,555 170,555q169 558 170 555);"/>
                    <Edge cubics="!170 555(;170,555 171,555 171,555q170 555 171 555);"/>
                    <Edge cubics="!-172 537(;-172,537 -173,537 -173,537q-172 537 -173 537);"/>
                    <Edge cubics="!-173 537(;-172,539 -170,540 -169,541q-173 537Q-171 540q-169 541);"/>
                    <Edge cubics="!-169 541(;-170,539 -171,538 -172,537q-169 541Q-171 539q-172 537);"/>
                    <Edge cubics="!91 93(;91,93 92,94 92,94q91 93 92 94);"/>
                    <Edge cubics="!92 94(;92,94 93,94 93,94q92 94 93 94);"/>
                    <Edge cubics="!89 99(;90,97 90,95 91,93q89 99Q90 96q91 93);"/>
                    <Edge cubics="!89 98(;89,98 89,99 89,99q89 98 89 99);"/>
                    <Edge cubics="!93 104(;93,104 94,104 94,104q93 104 94 104);"/>
                    <Edge cubics="!93 103(;93,103 93,104 93,104q93 103 93 104);"/>
                    <Edge cubics="!87 103(;88,101 88,99 89,98q87 103Q88 100q89 98);"/>
                    <Edge cubics="!94 95(;94,98 94,100 93,103q94 95Q94 99q93 103);"/>
                    <Edge cubics="!93 94(;93,94 94,95 94,95q93 94 94 95);"/>
                    <Edge cubics="!94 104(;95,104 95,104 96,104q94 104Q95 104q96 104);"/>
                    <Edge cubics="!93 112(;93,112 93,115 93,115q93 112 93 115);"/>
                    <Edge cubics="!98 106(;96,108 96,110 95,111q98 106Q96 109q95 111);"/>
                    <Edge cubics="!58 66(;58,66 57,66 57,66q58 66 57 66);"/>
                    <Edge cubics="!82 117(;82,117 82,115 82,115q82 117 82 115);"/>
                    <Edge cubics="!81 118(;82,118 82,118 82,117q81 118Q82 118q82 117);"/>
                    <Edge cubics="!82 115(;82,114 82,114 83,113q82 115Q82 114q83 113);"/>
                    <Edge cubics="!83 108(;83,108 84,108 84,108q83 108 84 108);"/>
                    <Edge cubics="!84 108(;84,108 84,107 84,107q84 108 84 107);"/>
                    <Edge cubics="!83 113(;83,113 83,108 83,108q83 113 83 108);"/>
                    <Edge cubics="!86 105(;86,105 86,104 86,104q86 105 86 104);"/>
                    <Edge cubics="!58 99(;58,99 58,97 58,97q58 99 58 97);"/>
                    <Edge cubics="!58 97(;57,98 57,98 57,99q58 97Q57 98q57 99);"/>
                    <Edge cubics="!57 99(;57,99 58,99 58,99q57 99 58 99);"/>
                    <Edge cubics="!84 107(;85,106 85,106 86,105q84 107Q85 106q86 105);"/>
                    <Edge cubics="!58 76(;58,76 58,74 58,74q58 76 58 74);"/>
                    <Edge cubics="!60 79(;60,79 61,78 61,78q60 79 61 78);"/>
                    <Edge cubics="!62 74(;62,75 62,77 62,78q62 74Q62 76q62 78);"/>
                    <Edge cubics="!58 80(;58,79 58,77 58,76q58 80Q58 78q58 76);"/>
                    <Edge cubics="!60 72(;62,74 61,76 60,79q60 72Q62 75q60 79);"/>
                    <Edge cubics="!58 74(;56,72 56,70 57,69q58 74Q56 71q57 69);"/>
                    <Edge cubics="!56 92(;56,91 56,91 57,91q56 92Q56 91q57 91);"/>
                    <Edge cubics="!57 91(;57,91 57,89 57,89q57 91 57 89);"/>
                    <Edge cubics="!59 86(;59,86 59,85 59,85q59 86 59 85);"/>
                    <Edge cubics="!57 89(;57,88 57,87 59,86q57 89Q57 87q59 86);"/>
                    <Edge cubics="!59 85(;58,83 58,81 58,80q59 85Q58 82q58 80);"/>
                    <Edge cubics="!53 69(;53,69 52,71 52,71q53 69 52 71);"/>
                    <Edge cubics="!52 71(;52,71 51,71 51,71q52 71 51 71);"/>
                    <Edge cubics="!51 71(;51,71 53,75 53,75q51 71 53 75);"/>
                    <Edge cubics="!53 96(;53,96 53,98 53,98q53 96 53 98);"/>
                    <Edge cubics="!53 98(;53,98 54,97 54,97q53 98 54 97);"/>
                    <Edge cubics="!50 107(;50,107 49,106 49,106q50 107 49 106);"/>
                    <Edge cubics="!50 107(;49,107 49,107 48,106q50 107Q49 107q48 106);"/>
                    <Edge cubics="!48 106(;48,106 49,106 49,106q48 106 49 106);"/>
                    <Edge cubics="!56 93(;56,93 56,92 56,92q56 93 56 92);"/>
                    <Edge cubics="!54 97(;55,96 55,94 56,93q54 97Q55 95q56 93);"/>
                    <Edge cubics="!53 75(;53,82 52,89 53,96q53 75Q54 86q53 96);"/>
                    <Edge cubics="!63 102(;62,91 63,79 62,69q63 102Q64 84q62 69);"/>
                    <Edge cubics="!62 69(;62,69 61,68 61,68q62 69 61 68);"/>
                    <Edge cubics="!61 68(;61,69 61,70 60,72q61 68Q61 69q60 72);"/>
                    <Edge cubics="!57 66(;55,67 54,69 53,69q57 66Q55 68q53 69);"/>
                    <Edge cubics="!86 104(;86,103 86,103 87,103q86 104Q86 103q87 103);"/>
                    <Edge cubics="!183 264(;183,264 184,265 184,265q183 264 184 265);"/>
                    <Edge cubics="!184 265(;184,265 183,265 183,265q184 265 183 265);"/>
                    <Edge cubics="!183 265(;183,265 182,264 182,264q183 265 182 264);"/>
                    <Edge cubics="!182 264(;182,264 183,264 183,264q182 264 183 264);"/>
                    <Edge cubics="!185 277(;185,277 186,275 186,275q185 277 186 275);"/>
                    <Edge cubics="!186 276(;186,276 185,277 185,277q186 276 185 277);"/>
                    <Edge cubics="!186 275(;186,275 186,276 186,276q186 275 186 276);"/>
                    <Edge cubics="!156 150(;156,150 156,152 156,152q156 150 156 152);"/>
                    <Edge cubics="!156 152(;156,152 155,151 155,151q156 152 155 151);"/>
                    <Edge cubics="!155 151(;155,151 155,150 155,150q155 151 155 150);"/>
                    <Edge cubics="!155 150(;155,150 156,150 156,150q155 150 156 150);"/>
                    <Edge cubics="!150 191(;150,190 150,190 151,190q150 191Q150 190q151 190);"/>
                    <Edge cubics="!151 191(;151,191 150,192 150,192q151 191 150 192);"/>
                    <Edge cubics="!151 190(;151,190 151,191 151,191q151 190 151 191);"/>
                    <Edge cubics="!150 192(;150,192 150,191 150,191q150 192 150 191);"/>
                    <Edge cubics="!95 177(;95,177 95,178 95,178q95 177 95 178);"/>
                    <Edge cubics="!94 178(;94,178 95,177 95,177q94 178 95 177);"/>
                    <Edge cubics="!95 178(;95,178 94,178 94,178q95 178 94 178);"/>
                    <Edge cubics="!92 175(;92,175 93,176 93,176q92 175 93 176);"/>
                    <Edge cubics="!92 176(;92,176 92,175 92,175q92 176 92 175);"/>
                    <Edge cubics="!93 176(;93,176 92,176 92,176q93 176 92 176);"/>
                    <Edge cubics="!96 181(;96,181 97,182 97,182q96 181 97 182);"/>
                    <Edge cubics="!98 191(;97,191 97,191 97,190q98 191Q97 191q97 190);"/>
                    <Edge cubics="!97 190(;97,190 98,190 98,190q97 190 98 190);"/>
                    <Edge cubics="!98 190(;98,190 98,191 98,191q98 190 98 191);"/>
                    <Edge cubics="!98 194(;98,194 98,193 98,193q98 194 98 193);"/>
                    <Edge cubics="!98 193(;99,192 99,193 99,194q98 193Q99 192q99 194);"/>
                    <Edge cubics="!97 183(;97,183 96,181 96,181q97 183 96 181);"/>
                    <Edge cubics="!97 182(;97,182 97,183 97,183q97 182 97 183);"/>
                    <Edge cubics="!99 194(;99,194 99,197 99,197q99 194 99 197);"/>
                    <Edge cubics="!90 119(;90,120 90,120 89,121q90 119Q90 120q89 121);"/>
                    <Edge cubics="!91 120(;90,120 90,120 90,119q91 120Q90 120q90 119);"/>
                    <Edge cubics="!90 122(;90,122 91,122 91,122q90 122 91 122);"/>
                    <Edge cubics="!89 121(;89,121 90,122 90,122q89 121 90 122);"/>
                    <Edge cubics="!91 122(;89,124 88,126 86,127q91 122Q88 125q86 127);"/>
                    <Edge cubics="!60 156(;60,156 60,155 60,155q60 156 60 155);"/>
                    <Edge cubics="!59 166(;59,166 58,166 58,166q59 166 58 166);"/>
                    <Edge cubics="!58 166(;58,166 58,167 58,167q58 166 58 167);"/>
                    <Edge cubics="!58 167(;58,167 59,166 59,166q58 167 59 166);"/>
                    <Edge cubics="!60 155(;59,157 59,157 59,158q60 155Q59 157q59 158);"/>
                    <Edge cubics="!59 158(;59,158 60,156 60,156q59 158 60 156);"/>
                    <Edge cubics="!82 130(;82,130 82,129 82,129q82 130 82 129);"/>
                    <Edge cubics="!82 129(;82,129 81,129 81,129q82 129 81 129);"/>
                    <Edge cubics="!81 129(;81,129 81,128 81,128q81 129 81 128);"/>
                    <Edge cubics="!83 128(;83,128 82,130 82,130q83 128 82 130);"/>
                    <Edge cubics="!84 129(;84,129 83,129 83,129q84 129 83 129);"/>
                    <Edge cubics="!85 127(;84,128 84,128 84,129q85 127Q84 128q84 129);"/>
                    <Edge cubics="!83 129(;83,129 83,128 83,128q83 129 83 128);"/>
                    <Edge cubics="!83 123(;83,123 83,120 83,120q83 123 83 120);"/>
                    <Edge cubics="!83 120(;83,120 82,120 82,120q83 120 82 120);"/>
                    <Edge cubics="!81 128(;82,127 83,125 83,123q81 128Q83 126q83 123);"/>
                    <Edge cubics="!57 219(;57,218 57,218 58,217q57 219Q57 218q58 217);"/>
                    <Edge cubics="!58 217(;58,217 58,218 58,218q58 217 58 218);"/>
                    <Edge cubics="!55 219(;55,219 57,220 57,220q55 219 57 220);"/>
                    <Edge cubics="!57 220(;57,220 56,220 56,220q57 220 56 220);"/>
                    <Edge cubics="!56 220(;56,220 55,219 55,219q56 220 55 219);"/>
                    <Edge cubics="!72 189(;72,189 72,190 72,190q72 189 72 190);"/>
                    <Edge cubics="!73 188(;73,188 72,189 72,189q73 188 72 189);"/>
                    <Edge cubics="!72 190(;73,189 73,189 73,188q72 190Q73 189q73 188);"/>
                    <Edge cubics="!75 185(;75,185 77,184 77,184q75 185 77 184);"/>
                    <Edge cubics="!76 184(;76,184 75,185 75,185q76 184 75 185);"/>
                    <Edge cubics="!77 184(;77,184 76,184 76,184q77 184 76 184);"/>
                    <Edge cubics="!54 195(;54,195 54,194 54,194q54 195 54 194);"/>
                    <Edge cubics="!53 195(;53,195 54,195 54,195q53 195 54 195);"/>
                    <Edge cubics="!54 194(;54,194 53,195 53,195q54 194 53 195);"/>
                    <Edge cubics="!86 127(;85,128 85,128 85,127q86 127Q85 128q85 127);"/>
                    <Edge cubics="!53 225(;54,224 54,224 56,223q53 225Q54 224q56 223);"/>
                    <Edge cubics="!56 223(;56,223 55,224 55,224q56 223 55 224);"/>
                    <Edge cubics="!55 224(;54,225 54,225 53,226q55 224Q54 225q53 226);"/>
                    <Edge cubics="!53 226(;53,226 53,225 53,225q53 226 53 225);"/>
                    <Edge cubics="!82 120(;82,120 81,118 81,118q82 120 81 118);"/>
                    <Edge cubics="!93 115(;92,116 92,118 91,120q93 115Q92 117q91 120);"/>
                    <Edge cubics="!-43 383(;-43,383 -42,383 -42,383q-43 383 -42 383);"/>
                    <Edge cubics="!-42 383(;-42,383 -43,382 -43,382q-42 383 -43 382);"/>
                    <Edge cubics="!-43 382(;-43,382 -43,383 -43,383q-43 382 -43 383);"/>
                    <Edge cubics="!-54 166(;-54,166 -54,167 -54,167q-54 166 -54 167);"/>
                    <Edge cubics="!-53 167(;-53,167 -54,166 -54,166q-53 167 -54 166);"/>
                    <Edge cubics="!-54 167(;-54,167 -53,167 -53,167q-54 167 -53 167);"/>
                    <Edge cubics="!-54 161(;-54,161 -54,160 -54,160q-54 161 -54 160);"/>
                    <Edge cubics="!-63 147(;-62,148 -62,149 -62,150q-63 147Q-62 149q-62 150);"/>
                    <Edge cubics="!-62 150(;-62,149 -62,149 -63,149q-62 150Q-62 149q-63 149);"/>
                    <Edge cubics="!-62 143(;-61,144 -60,146 -59,148q-62 143Q-61 145q-59 148);"/>
                    <Edge cubics="!-59 147(;-59,147 -58,147 -58,147q-59 147 -58 147);"/>
                    <Edge cubics="!-59 148(;-59,148 -59,147 -59,147q-59 148 -59 147);"/>
                    <Edge cubics="!-63 149(;-63,149 -63,147 -63,147q-63 149 -63 147);"/>
                    <Edge cubics="!-58 156(;-58,156 -58,157 -58,157q-58 156 -58 157);"/>
                    <Edge cubics="!-55 159(;-55,159 -56,159 -56,159q-55 159 -56 159);"/>
                    <Edge cubics="!-55 160(;-55,160 -55,161 -55,161q-55 160 -55 161);"/>
                    <Edge cubics="!-56 160(;-56,160 -55,159 -55,159q-56 160 -55 159);"/>
                    <Edge cubics="!-56 159(;-56,159 -56,160 -56,160q-56 159 -56 160);"/>
                    <Edge cubics="!-60 153(;-59,155 -59,155 -58,156q-60 153Q-59 155q-58 156);"/>
                    <Edge cubics="!-58 157(;-59,156 -59,155 -60,153q-58 157Q-59 156q-60 153);"/>
                    <Edge cubics="!-55 161(;-55,161 -54,161 -54,161q-55 161 -54 161);"/>
                    <Edge cubics="!-54 160(;-54,160 -55,160 -55,160q-54 160 -55 160);"/>
                    <Edge cubics="!-58 126(;-59,125 -59,125 -58,125q-58 126Q-59 125q-58 125);"/>
                    <Edge cubics="!-58 121(;-58,121 -59,120 -59,120q-58 121 -59 120);"/>
                    <Edge cubics="!-66 119(;-66,119 -67,119 -67,119q-66 119 -67 119);"/>
                    <Edge cubics="!-62 117(;-62,118 -62,118 -62,119q-62 117Q-62 118q-62 119);"/>
                    <Edge cubics="!-67 123(;-67,122 -66,120 -66,119q-67 123Q-66 121q-66 119);"/>
                    <Edge cubics="!-66 128(;-66,128 -64,129 -64,129q-66 128 -64 129);"/>
                    <Edge cubics="!-63 125(;-63,125 -63,126 -63,126q-63 125 -63 126);"/>
                    <Edge cubics="!-58 125(;-58,125 -58,121 -58,121q-58 125 -58 121);"/>
                    <Edge cubics="!-62 119(;-62,121 -63,123 -63,125q-62 119Q-63 122q-63 125);"/>
                    <Edge cubics="!-64 129(;-66,126 -67,125 -67,123q-64 129Q-67 126q-67 123);"/>
                    <Edge cubics="!-62 135(;-62,135 -62,136 -62,136q-62 135 -62 136);"/>
                    <Edge cubics="!-62 130(;-62,131 -62,133 -62,135q-62 130Q-62 132q-62 135);"/>
                    <Edge cubics="!-62 139(;-62,139 -63,141 -63,141q-62 139 -63 141);"/>
                    <Edge cubics="!-62 136(;-62,137 -62,138 -62,139q-62 136Q-62 137q-62 139);"/>
                    <Edge cubics="!-63 141(;-62,141 -62,141 -62,142q-63 141Q-62 141q-62 142);"/>
                    <Edge cubics="!-63 126(;-63,127 -62,129 -62,130q-63 126Q-63 128q-62 130);"/>
                    <Edge cubics="!-62 142(;-62,142 -62,143 -62,143q-62 142 -62 143);"/>
                    <Edge cubics="!-58 147(;-57,140 -57,133 -58,126q-58 147Q-57 137q-58 126);"/>
                    <Edge cubics="!-51 180(;-51,180 -51,181 -51,181q-51 180 -51 181);"/>
                    <Edge cubics="!-50 181(;-50,181 -51,180 -51,180q-50 181 -51 180);"/>
                    <Edge cubics="!-51 181(;-51,181 -50,181 -50,181q-51 181 -50 181);"/>
                    <Edge cubics="!-52 174(;-52,174 -50,175 -50,175q-52 174 -50 175);"/>
                    <Edge cubics="!-51 174(;-51,174 -52,174 -52,174q-51 174 -52 174);"/>
                    <Edge cubics="!-50 175(;-50,175 -51,174 -51,174q-50 175 -51 174);"/>
                    <Edge cubics="!-77 178(;-77,178 -77,177 -77,177q-77 178 -77 177);"/>
                    <Edge cubics="!-78 178(;-78,178 -77,178 -77,178q-78 178 -77 178);"/>
                    <Edge cubics="!-92 183(;-92,183 -93,183 -93,183q-92 183 -93 183);"/>
                    <Edge cubics="!-93 186(;-93,186 -94,185 -94,185q-93 186 -94 185);"/>
                    <Edge cubics="!-94 185(;-94,184 -94,184 -93,185q-94 185Q-94 184q-93 185);"/>
                    <Edge cubics="!-93 185(;-93,185 -93,186 -93,186q-93 185 -93 186);"/>
                    <Edge cubics="!-93 183(;-93,183 -93,182 -93,182q-93 183 -93 182);"/>
                    <Edge cubics="!-93 182(;-93,182 -92,183 -92,183q-93 182 -92 183);"/>
                    <Edge cubics="!-97 200(;-96,199 -96,198 -97,197q-97 200Q-96 199q-97 197);"/>
                    <Edge cubics="!-95 198(;-96,199 -96,199 -97,200q-95 198Q-96 199q-97 200);"/>
                    <Edge cubics="!-97 196(;-97,196 -96,194 -96,194q-97 196 -96 194);"/>
                    <Edge cubics="!-96 194(;-96,195 -96,197 -95,198q-96 194Q-96 196q-95 198);"/>
                    <Edge cubics="!-97 197(;-97,197 -97,196 -97,196q-97 197 -97 196);"/>
                    <Edge cubics="!-152 173(;-152,172 -152,172 -153,172q-152 173Q-152 172q-153 172);"/>
                    <Edge cubics="!-152 174(;-152,174 -152,173 -152,173q-152 174 -152 173);"/>
                    <Edge cubics="!-153 173(;-153,173 -152,174 -152,174q-153 173 -152 174);"/>
                    <Edge cubics="!-153 172(;-153,172 -153,173 -153,173q-153 172 -153 173);"/>
                    <Edge cubics="!-148 193(;-148,193 -148,192 -148,192q-148 193 -148 192);"/>
                    <Edge cubics="!-149 192(;-149,192 -148,193 -148,193q-149 192 -148 193);"/>
                    <Edge cubics="!-149 188(;-149,188 -149,187 -149,187q-149 188 -149 187);"/>
                    <Edge cubics="!-149 187(;-150,186 -150,186 -151,186q-149 187Q-150 186q-151 186);"/>
                    <Edge cubics="!-148 192(;-149,192 -149,192 -149,191q-148 192Q-149 192q-149 191);"/>
                    <Edge cubics="!-149 191(;-149,191 -149,192 -149,192q-149 191 -149 192);"/>
                    <Edge cubics="!-148 205(;-148,205 -148,206 -148,206q-148 205 -148 206);"/>
                    <Edge cubics="!-156 196(;-156,196 -157,195 -157,195q-156 196 -157 195);"/>
                    <Edge cubics="!-158 195(;-157,199 -158,203 -158,206q-158 195Q-158 201q-158 206);"/>
                    <Edge cubics="!-152 205(;-153,202 -154,199 -156,196q-152 205Q-154 201q-156 196);"/>
                    <Edge cubics="!-158 206(;-158,206 -152,205 -152,205q-158 206 -152 205);"/>
                    <Edge cubics="!-147 207(;-147,206 -147,206 -148,205q-147 207Q-147 206q-148 205);"/>
                    <Edge cubics="!-148 206(;-148,206 -147,207 -147,207q-148 206 -147 207);"/>
                    <Edge cubics="!-157 195(;-158,193 -158,194 -158,195q-157 195Q-158 193q-158 195);"/>
                    <Edge cubics="!-167 199(;-167,199 -167,201 -167,201q-167 199 -167 201);"/>
                    <Edge cubics="!-166 200(;-166,200 -167,199 -167,199q-166 200 -167 199);"/>
                    <Edge cubics="!-167 201(;-167,201 -166,201 -166,201q-167 201 -166 201);"/>
                    <Edge cubics="!-166 201(;-166,201 -166,200 -166,200q-166 201 -166 200);"/>
                    <Edge cubics="!-181 262(;-181,263 -181,263 -182,263q-181 262Q-181 263q-182 263);"/>
                    <Edge cubics="!-189 265(;-189,265 -187,266 -187,266q-189 265 -187 266);"/>
                    <Edge cubics="!-187 266(;-187,266 -188,265 -188,265q-187 266 -188 265);"/>
                    <Edge cubics="!-188 265(;-188,265 -189,265 -189,265q-188 265 -189 265);"/>
                    <Edge cubics="!-182 263(;-182,261 -182,260 -181,261q-182 263Q-182 260q-181 261);"/>
                    <Edge cubics="!-178 267(;-180,266 -180,264 -181,262q-178 267Q-181 264q-181 262);"/>
                    <Edge cubics="!-181 261(;-180,263 -180,265 -178,267q-181 261Q-179 264q-178 267);"/>
                    <Edge cubics="!-187 275(;-187,276 -187,276 -186,276q-187 275Q-187 276q-186 276);"/>
                    <Edge cubics="!-186 275(;-186,275 -187,275 -187,275q-186 275 -187 275);"/>
                    <Edge cubics="!-186 276(;-186,276 -186,275 -186,275q-186 276 -186 275);"/>
                    <Edge cubics="!-62 115(;-62,115 -63,115 -63,115q-62 115 -63 115);"/>
                    <Edge cubics="!-59 120(;-60,118 -61,116 -62,115q-59 120Q-60 117q-62 115);"/>
                    <Edge cubics="!-63 115(;-63,115 -62,117 -62,117q-63 115 -62 117);"/>
                    <Edge cubics="!-151 186(;-151,186 -149,188 -149,188q-151 186 -149 188);"/>
                    <Edge cubics="!-67 172(;-67,171 -67,170 -67,169q-67 172Q-67 171q-67 169);"/>
                    <Edge cubics="!-67 153(;-67,160 -68,166 -67,172q-67 153Q-68 163q-67 172);"/>
                    <Edge cubics="!-67 126(;-67,127 -67,127 -66,128q-67 126Q-67 127q-66 128);"/>
                    <Edge cubics="!95 111(;95,111 93,112 93,112q95 111 93 112);"/>
                    <Edge cubics="!61 80(;61,79 61,77 62,74q61 80Q61 78q62 74);"/>
                    <Edge cubics="!61 78(;61,79 61,79 61,80q61 78Q61 79q61 80);"/>
                    <Edge cubics="!57 69(;57,69 58,66 58,66q57 69 58 66);"/>
                    <Edge cubics="!99 197(;99,196 99,195 98,194q99 197Q99 196q98 194);"/>
                    <Edge cubics="!-67 119(;-67,121 -68,123 -67,126q-67 119Q-68 122q-67 126);"/>
                    <Edge cubics="!58 218(;57,218 57,218 57,219q58 218Q57 218q57 219);"/>
                    <Edge cubics="!96 104(;96,104 98,106 98,106q96 104 98 106);"/>
                    <Edge cubics="!-67 169(;-67,164 -67,158 -67,153q-67 169Q-67 161q-67 153);"/>
                    <Edge cubics="!62 110(;62,107 62,105 63,102q62 110Q62 106q63 102);"/>
                    <Edge cubics="!62 78(;62,89 62,99 62,110q62 78Q62 94q62 110);"/>
                  </edges>
                </DOMShape>
                <DOMShape isDrawingObject="true">
                  <matrix>
                    <Matrix a="-0.0018768310546875" b="0.5068359375" c="-0.5068359375" d="-0.0018768310546875" tx="-9.3" ty="5.65"/>
                  </matrix>
                  <fills>
                    <FillStyle index="1">
                      <SolidColor alpha="0.996078431372549"/>
                    </FillStyle>
                  </fills>
                  <strokes>
                    <StrokeStyle index="1">
                      <SolidStroke scaleMode="normal" weight="0.1">
                        <fill>
                          <SolidColor/>
                        </fill>
                      </SolidStroke>
                    </StrokeStyle>
                  </strokes>
                  <edges>
                    <Edge fillStyle1="1" strokeStyle="1" edges="
!440 -1060[639 -1060 779 -996!779 -996[920 -931 920 -840!920 -840[920 -749 779 -685!779 -685[639 -620 440 -620!440 -620[241 -620 100 -685!100 -685[-40 -749 -40 -840!-40 -840[-40 -931 100 -996!100 -996[241 -1060 440 -1060"/>
                  </edges>
                </DOMShape>
                <DOMShape isDrawingObject="true">
                  <matrix>
                    <Matrix a="-0.0018768310546875" b="0.5068359375" c="-0.5068359375" d="-0.0018768310546875" tx="-31.6" ty="5.3"/>
                  </matrix>
                  <fills>
                    <FillStyle index="1">
                      <SolidColor alpha="0.996078431372549"/>
                    </FillStyle>
                  </fills>
                  <strokes>
                    <StrokeStyle index="1">
                      <SolidStroke scaleMode="normal" weight="0.1">
                        <fill>
                          <SolidColor/>
                        </fill>
                      </SolidStroke>
                    </StrokeStyle>
                  </strokes>
                  <edges>
                    <Edge fillStyle1="1" strokeStyle="1" edges="
!440 -1060[639 -1060 779 -996!779 -996[920 -931 920 -840!920 -840[920 -749 779 -685!779 -685[639 -620 440 -620!440 -620[241 -620 100 -685!100 -685[-40 -749 -40 -840!-40 -840[-40 -931 100 -996!100 -996[241 -1060 440 -1060"/>
                  </edges>
                </DOMShape>
                <DOMShape isDrawingObject="true">
                  <matrix>
                    <Matrix a="-0.0018768310546875" b="0.5068359375" c="-0.5068359375" d="-0.0018768310546875" tx="1.35" ty="9.75"/>
                  </matrix>
                  <fills>
                    <FillStyle index="1">
                      <SolidColor color="#FF0000" alpha="0.996078431372549"/>
                    </FillStyle>
                  </fills>
                  <strokes>
                    <StrokeStyle index="1">
                      <SolidStroke scaleMode="normal" weight="0.1">
                        <fill>
                          <SolidColor/>
                        </fill>
                      </SolidStroke>
                    </StrokeStyle>
                  </strokes>
                  <edges>
                    <Edge fillStyle1="1" strokeStyle="1" edges="
!170 -283|170 -1060!170 -1060|573 -279!573 -279|170 -283"/>
                  </edges>
                </DOMShape>
                <DOMShape isDrawingObject="true">
                  <matrix>
                    <Matrix a="-0.0018768310546875" b="0.5068359375" c="-0.5068359375" d="-0.0018768310546875" tx="1.35" ty="9.75"/>
                  </matrix>
                  <fills>
                    <FillStyle index="1">
                      <SolidColor color="#FF0000" alpha="0.996078431372549"/>
                    </FillStyle>
                  </fills>
                  <strokes>
                    <StrokeStyle index="1">
                      <SolidStroke scaleMode="normal" weight="0.1">
                        <fill>
                          <SolidColor/>
                        </fill>
                      </SolidStroke>
                    </StrokeStyle>
                  </strokes>
                  <edges>
                    <Edge fillStyle1="1" strokeStyle="1" edges="
!569 389|160 1130!160 1130|160 357!160 357|569 389"/>
                  </edges>
                </DOMShape>
                <DOMShape isDrawingObject="true">
                  <matrix>
                    <Matrix a="-0.5068359375" b="-0.0018768310546875" c="0.0018768310546875" d="-0.5068359375" tx="3.9" ty="11.05"/>
                  </matrix>
                  <fills>
                    <FillStyle index="1">
                      <SolidColor color="#FF0000" alpha="0.996078431372549"/>
                    </FillStyle>
                  </fills>
                  <strokes>
                    <StrokeStyle index="1">
                      <SolidStroke scaleMode="normal" weight="0.1">
                        <fill>
                          <SolidColor/>
                        </fill>
                      </SolidStroke>
                    </StrokeStyle>
                  </strokes>
                  <edges>
                    <Edge fillStyle1="1" strokeStyle="1" edges="
!-80 -120|-80 300!-80 300|-960 300!-960 300|-960 -120!-960 -120|-80 -120"/>
                  </edges>
                </DOMShape>
                <DOMShape isDrawingObject="true">
                  <matrix>
                    <Matrix a="-0.5068359375" b="-0.0018768310546875" c="0.0018768310546875" d="-0.5068359375" tx="-29.35" ty="10.7"/>
                  </matrix>
                  <fills>
                    <FillStyle index="1">
                      <SolidColor color="#FF0000" alpha="0.996078431372549"/>
                    </FillStyle>
                  </fills>
                  <strokes>
                    <StrokeStyle index="1">
                      <SolidStroke scaleMode="normal" weight="0.1">
                        <fill>
                          <SolidColor/>
                        </fill>
                      </SolidStroke>
                    </StrokeStyle>
                  </strokes>
                  <edges>
                    <Edge fillStyle1="1" strokeStyle="1" edges="
!-80 -120|-80 300!-80 300|-960 300!-960 300|-960 -120!-960 -120|-80 -120"/>
                  </edges>
                </DOMShape>
                <DOMShape isDrawingObject="true">
                  <matrix>
                    <Matrix a="-0.5068359375" b="-0.0018768310546875" c="0.0018768310546875" d="-0.5068359375" tx="5.35" ty="17.1"/>
                  </matrix>
                  <fills>
                    <FillStyle index="1">
                      <SolidColor alpha="0.996078431372549"/>
                    </FillStyle>
                  </fills>
                  <strokes>
                    <StrokeStyle index="1">
                      <SolidStroke scaleMode="normal" weight="0.1">
                        <fill>
                          <SolidColor color="#FF0000"/>
                        </fill>
                      </SolidStroke>
                    </StrokeStyle>
                  </strokes>
                  <edges>
                    <Edge fillStyle1="1" strokeStyle="1" edges="
!474 -5[590 111 590 275!590 275[590 439 474 554!474 554[359 670 195 670!195 670[31 670 -85 554!-85 554[-200 439 -200 275!-200 275[-200 111 -85 -5!-85 -5[31 -120 195 -120!195 -120[359 -120 474 -5"/>
                  </edges>
                </DOMShape>
                <DOMShape isDrawingObject="true">
                  <matrix>
                    <Matrix a="-1.44621276855469" d="-1.80079650878906" tx="-2.95" ty="32.1"/>
                  </matrix>
                  <transformationPoint>
                    <Point x="-1.9" y="3.9"/>
                  </transformationPoint>
                  <fills>
                    <FillStyle index="1">
                      <SolidColor/>
                    </FillStyle>
                  </fills>
                  <strokes>
                    <StrokeStyle index="1">
                      <SolidStroke scaleMode="normal">
                        <fill>
                          <SolidColor color="#FF0000"/>
                        </fill>
                      </SolidStroke>
                    </StrokeStyle>
                  </strokes>
                  <edges>
                    <Edge fillStyle1="1" strokeStyle="1" edges="
!78 -37|78 194!78 194|-153 194!-153 194|-153 -37!-153 -37|78 -37"/>
                  </edges>
                </DOMShape>
                <DOMShape isDrawingObject="true">
                  <matrix>
                    <Matrix a="-1" d="-1" tx="0.7" ty="34"/>
                  </matrix>
                  <fills>
                    <FillStyle index="1">
                      <SolidColor color="#FF0000"/>
                    </FillStyle>
                  </fills>
                  <edges>
                    <Edge fillStyle1="1" edges="
!-161 349[-153 354 -153 371!-153 371[-153 #177.5C -156 376.5!-156 376.5[-155 #178.8F -155 378!-155 378[-155 379 -155 380!-155 380|-157 389!-157 389|-172 380!-172 380|-167 375!-167 375|-170 368!-170 368[-170 364 -166 366!-166 366|-161
 349"/>
                    <Edge cubics="!-161 349(;-156,352 -153,366 -153,371q-161 349Q-153 354q-153 371);"/>
                    <Edge cubics="!-153 371(;-153,374 -152,376 -157,377q-153 371Q-153 376q-157 377);"/>
                    <Edge cubics="!-157 377(;-154,375 -155,380 -155,380q-157 377Q-155 376q-155 378Q-155 379q-155 380);"/>
                    <Edge cubics="!-155 380(;-155,383 -156,386 -157,389q-155 380 -157 389);"/>
                    <Edge cubics="!-157 389(;-159,388 -169,381 -172,380q-157 389 -172 380);"/>
                    <Edge cubics="!-172 380(;-169,376 -169,376 -167,375q-172 380 -167 375);"/>
                    <Edge cubics="!-167 375(;-167,374 -170,368 -170,368q-167 375 -170 368);"/>
                    <Edge cubics="!-170 368(;-170,365 -168,365 -166,366q-170 368Q-170 364q-166 366);"/>
                    <Edge cubics="!-166 366(;-165,361 -162,354 -161,349q-166 366 -161 349);"/>
                  </edges>
                </DOMShape>
              </elements>
            </DOMFrame>
          </frames>
        </DOMLayer>
        <DOMLayer name="Layer 7" color="#4F80FF">
          <frames>
            <DOMFrame index="0" keyMode="9728">
              <elements/>
            </DOMFrame>
          </frames>
        </DOMLayer>
      </layers>
    </DOMTimeline>
  </timeline>
</DOMSymbolItem>