<DOMSymbolItem xmlns:xsi="http://www.w3.org/2001/XMLSchema-instance" xmlns="http://ns.adobe.com/xfl/2008/" name="YouHaveLost" itemID="509597b3-0000010b" linkageExportForAS="true" linkageClassName="YouHaveLost" lastModified="1359688497">
  <timeline>
    <DOMTimeline name="YouHaveLost" currentFrame="29">
      <layers>
        <DOMLayer name="Layer 2" color="#9933CC">
          <frames>
            <DOMFrame index="0" duration="29" keyMode="9728">
              <elements/>
            </DOMFrame>
            <DOMFrame index="29" keyMode="9728">
              <Actionscript>
                <script><![CDATA[stop();]]></script>
              </Actionscript>
              <elements/>
            </DOMFrame>
          </frames>
        </DOMLayer>
        <DOMLayer name="Layer 1" color="#4FFF4F" current="true" isSelected="true" animationType="motion object">
          <frames>
            <DOMFrame index="0" duration="30" tweenType="motion object" motionTweenRotate="none" motionTweenScale="false" isMotionObject="true" visibleAnimationKeyframes="2097151" keyMode="8195">
              <motionObjectXML><AnimationCore TimeScale="30000" Version="1" duration="30000"><TimeMap strength="0" type="Quadratic"/><metadata><names><name langID="en_GB" value=""/></names><Settings orientToPath="0" xformPtXOffsetPct="0.130841" xformPtYOffsetPct="0.213073" xformPtZOffsetPixels="0"/></metadata><PropertyContainer id="headContainer"><PropertyContainer id="Basic_Motion"><Property enabled="1" id="Motion_X" ignoreTimeMap="0" readonly="0" visible="1"><Keyframe anchor="0,0" next="0,0" previous="0,0" roving="0" timevalue="0"/><Keyframe anchor="0,0" next="0,0" previous="0,0" roving="0" timevalue="29000"/></Property><Property enabled="1" id="Motion_Y" ignoreTimeMap="0" readonly="0" visible="1"><Keyframe anchor="0,0" next="0,0" previous="0,0" roving="0" timevalue="0"/><Keyframe anchor="0,297.45" next="0,297.45" previous="0,297.45" roving="0" timevalue="29000"/></Property><Property enabled="1" id="Rotation_Z" ignoreTimeMap="0" readonly="0" visible="1"><Keyframe anchor="0,0" next="0,0" previous="0,0" roving="0" timevalue="0"/></Property></PropertyContainer><PropertyContainer id="Transformation"><Property enabled="1" id="Skew_X" ignoreTimeMap="0" readonly="0" visible="1"><Keyframe anchor="0,0" next="0,0" previous="0,0" roving="0" timevalue="0"/></Property><Property enabled="1" id="Skew_Y" ignoreTimeMap="0" readonly="0" visible="1"><Keyframe anchor="0,0" next="0,0" previous="0,0" roving="0" timevalue="0"/></Property><Property enabled="1" id="Scale_X" ignoreTimeMap="0" readonly="0" visible="1"><Keyframe anchor="0,100" next="0,100" previous="0,100" roving="0" timevalue="0"/><Keyframe anchor="0,107.777" next="0,107.777" previous="0,107.777" roving="0" timevalue="29000"/></Property><Property enabled="1" id="Scale_Y" ignoreTimeMap="0" readonly="0" visible="1"><Keyframe anchor="0,100" next="0,100" previous="0,100" roving="0" timevalue="0"/><Keyframe anchor="0,160.239" next="0,160.239" previous="0,160.239" roving="0" timevalue="29000"/></Property></PropertyContainer><PropertyContainer id="Colors"/><PropertyContainer id="Filters"/></PropertyContainer></AnimationCore></motionObjectXML>
              <elements>
                <DOMStaticText selected="true" width="584.5" height="214" autoExpand="true" isSelectable="false">
                  <matrix>
                    <Matrix tx="-280.65" ty="2"/>
                  </matrix>
                  <transformationPoint>
                    <Point x="75" y="44.45"/>
                  </transformationPoint>
                  <textRuns>
                    <DOMTextRun>
                      <characters>     &#xD;You have Lost</characters>
                      <textAttrs>
                        <DOMTextAttrs aliasText="false" size="80" bitmapSize="1600" face="Algerian" fillColor="#FFFFFF"/>
                      </textAttrs>
                    </DOMTextRun>
                  </textRuns>
                </DOMStaticText>
              </elements>
            </DOMFrame>
          </frames>
        </DOMLayer>
      </layers>
    </DOMTimeline>
  </timeline>
</DOMSymbolItem>